symphony/__init__.py
symphony/bdk/__init__.py
symphony/bdk/core/__init__.py
symphony/bdk/core/activity/__init__.py
symphony/bdk/core/activity/api.py
symphony/bdk/core/activity/command.py
symphony/bdk/core/activity/exception.py
symphony/bdk/core/activity/form.py
symphony/bdk/core/activity/help_command.py
symphony/bdk/core/activity/parsing/arguments.py
symphony/bdk/core/activity/parsing/command_token.py
symphony/bdk/core/activity/parsing/input_tokenizer.py
symphony/bdk/core/activity/parsing/match_result.py
symphony/bdk/core/activity/parsing/message_entities.py
symphony/bdk/core/activity/parsing/slash_command_pattern.py
symphony/bdk/core/activity/registry.py
symphony/bdk/core/activity/user_joined_room.py
symphony/bdk/core/auth/__init__.py
symphony/bdk/core/auth/auth_session.py
symphony/bdk/core/auth/authenticator_factory.py
symphony/bdk/core/auth/bot_authenticator.py
symphony/bdk/core/auth/exception.py
symphony/bdk/core/auth/ext_app_authenticator.py
symphony/bdk/core/auth/jwt_helper.py
symphony/bdk/core/auth/obo_authenticator.py
symphony/bdk/core/auth/tokens_repository.py
symphony/bdk/core/client/__init__.py
symphony/bdk/core/client/api_client_factory.py
symphony/bdk/core/client/trace_id.py
symphony/bdk/core/config/__init__.py
symphony/bdk/core/config/exception.py
symphony/bdk/core/config/loader.py
symphony/bdk/core/config/model/__init__.py
symphony/bdk/core/config/model/bdk_app_config.py
symphony/bdk/core/config/model/bdk_authentication_config.py
symphony/bdk/core/config/model/bdk_bot_config.py
symphony/bdk/core/config/model/bdk_certificate_config.py
symphony/bdk/core/config/model/bdk_client_config.py
symphony/bdk/core/config/model/bdk_config.py
symphony/bdk/core/config/model/bdk_datafeed_config.py
symphony/bdk/core/config/model/bdk_datahose_config.py
symphony/bdk/core/config/model/bdk_retry_config.py
symphony/bdk/core/config/model/bdk_rsa_key_config.py
symphony/bdk/core/config/model/bdk_server_config.py
symphony/bdk/core/config/model/bdk_ssl_config.py
symphony_bdk_python-2.11.1.dist-info/LICENSE
symphony_bdk_python-2.11.1.dist-info/METADATA
symphony_bdk_python-2.11.1.dist-info/NOTICE
symphony_bdk_python-2.11.1.dist-info/WHEEL
symphony_bdk_python-2.11.1.dist-info/RECORD
