Metadata-Version: 2.3
Name: symphony_bdk_python
Version: 2.11.1
Summary: Symphony Bot Development Kit for Python
License: Apache-2.0
Author: Symphony Platform Solutions
Author-email: symphony@finos.org
Requires-Python: >=3.9, !=2.7.*, !=3.0.*, !=3.1.*, !=3.2.*, !=3.3.*, !=3.4.*, !=3.5.*, !=3.6.*, !=3.7.*, !=3.8.*
Classifier: License :: OSI Approved :: Apache Software License
Classifier: Programming Language :: Python :: 3
Classifier: Programming Language :: Python :: 3.10
Classifier: Programming Language :: Python :: 3.11
Classifier: Programming Language :: Python :: 3.12
Classifier: Programming Language :: Python :: 3.13
Requires-Dist: PyJWT (>=2.10.0,<3.0.0)
Requires-Dist: aiohttp (>=3.12.14,<4.0.0)
Requires-Dist: cryptography (>=44.0.1,<45.0.0)
Requires-Dist: defusedxml (>=0.7.1,<0.8.0)
Requires-Dist: docutils (==0.16)
Requires-Dist: nulltype (>=2.3.1,<3.0.0)
Requires-Dist: python-dateutil (>=2.8.2,<3.0.0)
Requires-Dist: pyyaml (>=6.0,<7.0)
Requires-Dist: tenacity (>=8.0.1,<9.0.0)
Requires-Dist: urllib3 (>=2.5.0,<3)
Project-URL: Documentation, https://symphony-bdk-python.finos.org/
Project-URL: Repository, https://github.com/finos/symphony-bdk-python
